pymemtrace/__init__.py
pymemtrace/cMemLeak.cpython-38-darwin.so
pymemtrace/cPyMemTrace.cpython-38-darwin.so
pymemtrace/custom.cpython-38-darwin.so
pymemtrace/debug_malloc_stats.py
pymemtrace/parse_dtrace_output.py
pymemtrace/process.py
pymemtrace/redirect_stdout.py
pymemtrace/trace_malloc.py
pymemtrace/examples/__init__.py
pymemtrace/examples/ex_cPyMemTrace.py
pymemtrace/examples/ex_debug_malloc_stats.py
pymemtrace/examples/ex_dtrace.py
pymemtrace/examples/ex_memory_exercise.py
pymemtrace/examples/ex_process.py
pymemtrace/examples/ex_trace_malloc.py
pymemtrace/examples/example.py
pymemtrace/src/c/get_rss.c
pymemtrace/src/c/pymemtrace_util.c
pymemtrace/src/cpy/cCustom.c
pymemtrace/src/cpy/cMemLeak.c
pymemtrace/src/cpy/cPyMemTrace.c
pymemtrace/src/include/get_rss.h
pymemtrace/src/include/pymemtrace_util.h
tests/__init__.py
tests/_test_redirect_stdout.py
tests/test_cMemLeak.py
tests/test_cpymemtrace.py
tests/test_debug_malloc_stats.py
tests/test_process.py
tests/test_settrace.py
tests/test_trace_malloc.py
pymemtrace-0.2.0.dist-info/AUTHORS.rst
pymemtrace-0.2.0.dist-info/LICENSE
pymemtrace-0.2.0.dist-info/METADATA
pymemtrace-0.2.0.dist-info/WHEEL
pymemtrace-0.2.0.dist-info/top_level.txt
pymemtrace-0.2.0.dist-info/RECORD
