Metadata-Version: 2.1
Name: pymemtrace
Version: 0.2.0
Summary: Python memory tracing.
Home-page: https://github.com/paulross/pymemtrace
Author: Paul Ross
Author-email: apaulross@gmail.com
License: MIT license
Keywords: pymemtrace
Classifier: Development Status :: 3 - Alpha
Classifier: Intended Audience :: Developers
Classifier: License :: OSI Approved :: MIT License
Classifier: Natural Language :: English
Classifier: Programming Language :: C
Classifier: Programming Language :: Python :: 3 :: Only
Classifier: Programming Language :: Python :: Implementation :: CPython
Classifier: Programming Language :: Python :: 3.7
Classifier: Programming Language :: Python :: 3.8
Classifier: Programming Language :: Python :: 3.9
Classifier: Programming Language :: Python :: 3.10
Classifier: Programming Language :: Python :: 3.11
Classifier: Programming Language :: Python :: 3.12
Classifier: Programming Language :: Python :: 3.13
Classifier: Topic :: Software Development
License-File: LICENSE
License-File: AUTHORS.rst
Requires-Dist: psutil
